[
  {
    "title": "Slime legion",
    "link": {
      "demo": "https://slime-legion.vercel.app/",
      "code": "https://github.com/kaehehehe/slime-legion"
    }
  },
  {
    "title": "Tiffany Gift Boxes",
    "link": {
      "demo": "https://tiffany-gift-boxes.vercel.app/",
      "code": "https://github.com/kaehehehe/tiffany-gift-boxes"
    }
  },
  {
    "title": "Valentine balloon",
    "link": {
      "demo": "https://valentine-balloon.vercel.app/",
      "code": "https://github.com/kaehehehe/valentine-balloon"
    }
  },
  {
    "title": "Soft serve ice cream",
    "link": {
      "demo": "https://soft-serve-ice-cream.vercel.app/",
      "code": "https://github.com/kaehehehe/soft-serve-ice-cream"
    }
  },
  {
    "title": "Strawberry",
    "link": {
      "demo": "https://strawberry-wonderland.vercel.app/",
      "code": "https://github.com/kaehehehe/strawberry-wonderland"
    }
  },
  {
    "title": "Cherry",
    "link": {
      "demo": "https://cherry-cherry-cherry.vercel.app/",
      "code": "https://github.com/kaehehehe/cherry"
    }
  },
  {
    "title": "Lipsticks",
    "link": {
      "demo": "https://kaehehehe-lipsticks.vercel.app/",
      "code": "https://github.com/kaehehehe/lipsticks"
    }
  },
  {
    "title": "Retro phone",
    "link": {
      "demo": "https://kaehehehe-retro-phone.vercel.app/",
      "code": "https://github.com/kaehehehe/retro-phone"
    }
  },
  {
    "title": "Star candy",
    "link": {
      "demo": "https://kaehehehe-star-candy.vercel.app/",
      "code": "https://github.com/kaehehehe/star-candy"
    }
  },
  {
    "title": "Diamond",
    "link": {
      "demo": "https://kaehehehe-diamond.vercel.app/",
      "code": "https://github.com/kaehehehe/diamond"
    }
  },
  {
    "title": "Balloon dog",
    "link": {
      "demo": "https://balloon-dog.vercel.app/",
      "code": "https://github.com/kaehehehe/balloon-dog"
    }
  },
  {
    "title": "Record player",
    "link": {
      "demo": "https://kaehehehe-record-player.vercel.app/",
      "code": "https://github.com/kaehehehe/record-player"
    }
  },
  {
    "title": "Magneton",
    "link": {
      "demo": "https://pokemon-magneton.vercel.app/",
      "code": "https://github.com/kaehehehe/magneton"
    }
  }
]
